{"pageContext":{"isCreatedByStatefulCreatePages":false,"candidate":{"id":329,"party":"民主進步黨","name":"柯建銘","is_elected":true,"num_of_vote":"90642","rate_of_vote":"41.33","finance_data":{"income":{"個人捐贈收入":{"name":"個人捐贈收入","amount":21483455,"item_count":354},"營利事業捐贈收入":{"name":"營利事業捐贈收入","amount":26915133,"item_count":51},"政黨捐贈收入":{"name":"政黨捐贈收入","amount":0,"item_count":0},"人民團體捐贈收入":{"name":"人民團體捐贈收入","amount":3020000,"item_count":9},"匿名捐贈":{"name":"匿名捐贈","amount":222011,"item_count":37},"其他收入":{"name":"其他收入","amount":548,"item_count":1},"top100":[{"amount":2000000,"object":"台北馥敦飯店股份有限公司","type":"營利事業捐贈收入"},{"amount":1000000,"object":"建懋投資股份有限公司","type":"營利事業捐贈收入"},{"amount":1000000,"object":"建新國際股份有限公司","type":"營利事業捐贈收入"},{"amount":1000000,"object":"迅捷投資股份有限公司","type":"營利事業捐贈收入"},{"amount":1000000,"object":"弘鼎創業投資股份有限公司","type":"營利事業捐贈收入"},{"amount":1000000,"object":"智原科技股份有限公司","type":"營利事業捐贈收入"},{"amount":1000000,"object":"家瑞建設股份有限公司","type":"營利事業捐贈收入"},{"amount":1000000,"object":"閎業投資股份有限公司","type":"營利事業捐贈收入"},{"amount":1000000,"object":"德勤投資股份有限公司","type":"營利事業捐贈收入"},{"amount":1000000,"object":"百鼎投資股份有限公司","type":"營利事業捐贈收入"},{"amount":1000000,"object":"新合投資股份有限公司","type":"營利事業捐贈收入"},{"amount":1000000,"object":"得鋐投資股份有限公司","type":"營利事業捐贈收入"},{"amount":1000000,"object":"裕鋐投資股份有限公司","type":"營利事業捐贈收入"},{"amount":1000000,"object":"先銳投資股份有限公司","type":"營利事業捐贈收入"},{"amount":1000000,"object":"僑虹投資股份有限公司","type":"營利事業捐贈收入"},{"amount":1000000,"object":"創見投資股份有限公司","type":"營利事業捐贈收入"},{"amount":1000000,"object":"聯虹投資股份有限公司","type":"營利事業捐贈收入"},{"amount":1000000,"object":"宏林營造廠股份有限公司","type":"營利事業捐贈收入"},{"amount":1000000,"object":"社團法人新竹市牙醫師公會","type":"人民團體捐贈收入"},{"amount":900000,"object":"香樹花園酒店股份有限公司","type":"營利事業捐贈收入"},{"amount":800000,"object":"台灣區電氣工程工業同業公會","type":"人民團體捐贈收入"},{"amount":500000,"object":"華碩聯合科技股份有限公司","type":"營利事業捐贈收入"},{"amount":500000,"object":"全昌益房屋仲介股份有限公司","type":"營利事業捐贈收入"},{"amount":500000,"object":"美周貿易股份有限公司","type":"營利事業捐贈收入"},{"amount":500000,"object":"遠興化學工業股份有限公司","type":"營利事業捐贈收入"},{"amount":500000,"object":"百加利股份有限公司","type":"營利事業捐贈收入"},{"amount":500000,"object":"新竹縣不動產開發商業同業公會","type":"人民團體捐贈收入"},{"amount":300000,"object":"軍陽股份有限公司","type":"營利事業捐贈收入"},{"amount":300000,"object":"舜威都市開發股份有限公司","type":"營利事業捐贈收入"},{"amount":300000,"object":"揚昌汽車有限公司","type":"營利事業捐贈收入"},{"amount":300000,"object":"中台資源科技股份有限公司","type":"營利事業捐贈收入"},{"amount":300000,"object":"觀鼎企業有限公司","type":"營利事業捐贈收入"},{"amount":300000,"object":"富旺國際開發股份有限公司","type":"營利事業捐贈收入"},{"amount":300000,"object":"安普新股份有限公司","type":"營利事業捐贈收入"},{"amount":300000,"object":"永恆營造股份有限公司","type":"營利事業捐贈收入"},{"amount":300000,"object":"金益鼎企業股份有限公司","type":"營利事業捐贈收入"},{"amount":300000,"object":"新竹市不動產開發商業同業公會","type":"人民團體捐贈收入"},{"amount":200000,"object":"五崧捷運股份有限公司","type":"營利事業捐贈收入"},{"amount":200000,"object":"榮錦建設股份有限公司","type":"營利事業捐贈收入"},{"amount":200000,"object":"碩禾電子材料股份有限公司","type":"營利事業捐贈收入"},{"amount":200000,"object":"厚聚能源開發股份有限公司","type":"營利事業捐贈收入"},{"amount":200000,"object":"聯賓塑膠股份有限公司","type":"營利事業捐贈收入"},{"amount":200000,"object":"社團法人新竹市中醫師公會","type":"人民團體捐贈收入"},{"amount":120000,"object":"花蓮縣不動產開發商業同業公會","type":"人民團體捐贈收入"},{"amount":100000,"object":"洽隆企業有限公司","type":"營利事業捐贈收入"},{"amount":100000,"object":"峻源股份有限公司","type":"營利事業捐贈收入"},{"amount":100000,"object":"東霙營造股份有限公司","type":"營利事業捐贈收入"},{"amount":100000,"object":"太得投資有限公司","type":"營利事業捐贈收入"},{"amount":100000,"object":"元智汽車股份有限公司","type":"營利事業捐贈收入"},{"amount":100000,"object":"暐順營造股份有限公司","type":"營利事業捐贈收入"},{"amount":100000,"object":"新竹市醫師公會","type":"人民團體捐贈收入"},{"amount":82045,"object":"興學文化事業股份有限公司","type":"營利事業捐贈收入"},{"amount":50000,"object":"好力國際股份有限公司","type":"營利事業捐贈收入"},{"amount":36288,"object":"百祥加油站股份有限公司","type":"營利事業捐贈收入"},{"amount":30000,"object":"東家通建設有限公司","type":"營利事業捐贈收入"},{"amount":16800,"object":"國生企業有限公司","type":"營利事業捐贈收入"}]},"outcome":{"人事費用支出":{"name":"人事費用支出","amount":55960,"item_count":8},"宣傳支出":{"name":"宣傳支出","amount":36548691,"item_count":229},"租用宣傳車輛支出":{"name":"租用宣傳車輛支出","amount":0,"item_count":0},"租用競選辦事處支":{"name":"租用競選辦事處支","amount":1200000,"item_count":4},"集會支出":{"name":"集會支出","amount":6076630,"item_count":20},"交通旅運支出":{"name":"交通旅運支出","amount":766241,"item_count":12},"雜支支出":{"name":"雜支支出","amount":6222119,"item_count":181},"返還支出":{"name":"返還支出","amount":1296800,"item_count":6},"繳庫支出":{"name":"繳庫支出","amount":0,"item_count":0},"公共關係費用支出":{"name":"公共關係費用支出","amount":21490,"item_count":6},"top100":[{"amount":4000000,"object":"鴻泰印刷所","type":"宣傳支出"},{"amount":3779160,"object":"集智館文化有限公司","type":"宣傳支出"},{"amount":2765000,"object":"亂影數碼製作有限公司","type":"宣傳支出"},{"amount":2666880,"object":"奈克廣告創意行銷有限公司","type":"集會支出"},{"amount":2575751,"object":"人因創智有限公司","type":"宣傳支出"},{"amount":2503750,"object":"大千包裝實業有限公司","type":"宣傳支出"},{"amount":2480000,"object":"國幸廣告有限公司","type":"宣傳支出"},{"amount":1961400,"object":"綺美廣告社","type":"宣傳支出"},{"amount":1717682,"object":"中華郵政股份有限公司新竹武昌街郵局","type":"宣傳支出"},{"amount":1700000,"object":"薪揚廣告有限公司","type":"宣傳支出"},{"amount":1628000,"object":"全成廣告社","type":"宣傳支出"},{"amount":1318000,"object":"豪記音響有限公司","type":"集會支出"},{"amount":1315613,"object":"飛旭國際有限公司","type":"宣傳支出"},{"amount":1269450,"object":"歐樺設計印刷品有限公司","type":"宣傳支出"},{"amount":1200000,"object":"福村建設股份有限公司","type":"租用競選辦事處支"},{"amount":1000000,"object":"赫譜文化事業股份有限公司","type":"宣傳支出"},{"amount":906675,"object":"強葳國際有限公司","type":"宣傳支出"},{"amount":800000,"object":"喧嘩股份有限公司","type":"集會支出"},{"amount":790150,"object":"元新國際行銷有限公司","type":"宣傳支出"},{"amount":612250,"object":"好玩的劇團","type":"集會支出"},{"amount":505785,"object":"全聚廣告有限公司","type":"宣傳支出"},{"amount":465000,"object":"環宇廣播事業股份有限公司","type":"宣傳支出"},{"amount":417600,"object":"今周文化事業股份有限公司","type":"宣傳支出"},{"amount":397530,"object":"奈克廣告創意行銷有限公司","type":"宣傳支出"},{"amount":357000,"object":"環宇整合行銷股份有限公司","type":"宣傳支出"},{"amount":341250,"object":"大豐旗幟有限公司","type":"宣傳支出"},{"amount":320000,"object":"亞巨光電有限公司","type":"宣傳支出"},{"amount":302400,"object":"中國廣播股份有限公司","type":"宣傳支出"},{"amount":294000,"object":"國信傳播事業有限公司","type":"宣傳支出"},{"amount":277200,"object":"中時中華廣告服務有限公司","type":"宣傳支出"},{"amount":250000,"object":"飛揚廣播股份有限公司","type":"宣傳支出"},{"amount":250000,"object":"方舟音樂文化有限公司","type":"集會支出"},{"amount":249480,"object":"互為主體廣告股份有限公司","type":"宣傳支出"},{"amount":240000,"object":"宜昌百貨行","type":"宣傳支出"},{"amount":220000,"object":"克里斯與藍尼製作工作室","type":"宣傳支出"},{"amount":220000,"object":"風之藝術工作室有限公司","type":"集會支出"},{"amount":197500,"object":"欣源企業有限公司","type":"宣傳支出"},{"amount":190000,"object":"竹科廣播股份有限公司","type":"宣傳支出"},{"amount":160000,"object":"台灣數位多媒體有限公司","type":"宣傳支出"},{"amount":150000,"object":"牛奶人工作室","type":"宣傳支出"},{"amount":150000,"object":"民報文化事業股份有限公司","type":"宣傳支出"},{"amount":126000,"object":"睿軒廣告社","type":"宣傳支出"},{"amount":100320,"object":"中華郵政股份有限公司新竹武昌街局","type":"宣傳支出"},{"amount":95000,"object":"風采餐飲事業開發股份有限公司","type":"集會支出"},{"amount":82950,"object":"中時中華廣告務務有限公司","type":"宣傳支出"},{"amount":70350,"object":"創益動力股份有限公司","type":"宣傳支出"},{"amount":65000,"object":"御鼓坊","type":"集會支出"},{"amount":63000,"object":"韓昌福光能科技有限公司","type":"宣傳支出"},{"amount":42000,"object":"開心廣告有限公司","type":"宣傳支出"},{"amount":40000,"object":"時報資訊股份有限公司","type":"宣傳支出"},{"amount":35910,"object":"大薪竹廣告工程有限公司","type":"宣傳支出"},{"amount":33000,"object":"鉅仕企業社","type":"集會支出"},{"amount":28000,"object":"莊煥禎","type":"人事費用支出"},{"amount":24974,"object":"丹燕廣告有限公司","type":"宣傳支出"},{"amount":22450,"object":"晶華國際酒店股份有限公司","type":"宣傳支出"},{"amount":21490,"object":"晴晴花藝有限公司","type":"公共關係費用支出"},{"amount":18743,"object":"礱騰科技有限公司","type":"宣傳支出"},{"amount":17500,"object":"金塔廣告事業工程行","type":"宣傳支出"},{"amount":12688,"object":"新竹物流股份有限公司","type":"宣傳支出"},{"amount":12000,"object":"鄭克偉","type":"人事費用支出"},{"amount":11500,"object":"舊是經典有限公司","type":"集會支出"},{"amount":7680,"object":"可洛音樂坊","type":"宣傳支出"},{"amount":6750,"object":"永玖打字行","type":"宣傳支出"},{"amount":5000,"object":"洽久聲環保股份有限公司","type":"集會支出"},{"amount":4000,"object":"周世國","type":"人事費用支出"},{"amount":4000,"object":"林欣瑩","type":"人事費用支出"},{"amount":4000,"object":"盧怡君","type":"人事費用支出"},{"amount":3960,"object":"徐菁","type":"人事費用支出"}]}},"tenders":[{"name":"中台資源科技股份有限公司","total_amount":379995,"item":[{"date":20160509,"file_name":"BDM-1-51839047","unit_name":"台灣中油股份有限公司","title":"廢汞清理工作","amount":379995,"winner":["中台資源科技股份有限公司"],"tender_api_url":"http://pcc.g0v.ronny.tw/api/tender?unit_id=3.13.50&job_number=EGF0523001","decisionDate":20160506}]},{"name":"厚聚能源開發股份有限公司","total_amount":5362608,"item":[{"date":20160824,"file_name":"BDM-1-51924584","unit_name":"嘉義市政府環境保護局","title":"105年度民間參與嘉義市市有公用不動產設置太陽光電發電系統計畫","amount":0,"winner":["厚聚能源開發股份有限公司"],"tender_api_url":"http://pcc.g0v.ronny.tw/api/tender?unit_id=3.76.60.3.6&job_number=1050739","decisionDate":20160826},{"date":20160829,"file_name":"BDM-1-51927239","unit_name":"嘉義市政府環境保護局","title":"105年度民間參與嘉義市市有公用不動產設置太陽光電發電系統計畫","amount":0,"winner":["厚聚能源開發股份有限公司"],"tender_api_url":"http://pcc.g0v.ronny.tw/api/tender?unit_id=3.76.60.3.6&job_number=1050739","decisionDate":20160826},{"date":20170126,"file_name":"BDM-1-52060296","unit_name":"國立屏東女子高級中學","title":"國立屏東女子高級中學屋頂出租設置太陽光電發電設備標租案","amount":52608,"winner":["厚聚能源開發股份有限公司"],"tender_api_url":"http://pcc.g0v.ronny.tw/api/tender?unit_id=3.92.1.69&job_number=10601","decisionDate":20170125},{"date":20170405,"file_name":"BDM-1-52105472","unit_name":"臺灣嘉南農田水利會","title":"芒子芒埤水面型太陽光電發電系統計畫","amount":5310000,"winner":["厚聚能源開發股份有限公司"],"tender_api_url":"http://pcc.g0v.ronny.tw/api/tender?unit_id=69118503&job_number=CN-P10601","decisionDate":20170329}]},{"name":"建新國際股份有限公司","total_amount":310000,"item":[{"date":20180409,"file_name":"BDM-1-52414092","unit_name":"臺灣港務股份有限公司臺中港務分公司","title":"「23號碼頭後線室內外消防設備」財物採購","amount":310000,"winner":["建新國際股份有限公司"],"tender_api_url":"http://pcc.g0v.ronny.tw/api/tender?unit_id=3.15.86.2&job_number=A2P170521","decisionDate":20180321}]},{"name":"金益鼎企業股份有限公司","total_amount":8068259,"item":[{"date":20170512,"file_name":"BDM-1-52136791","unit_name":"台灣中油股份有限公司","title":"大林煉油廠廢觸媒中貴金屬白金(Pt)回收工作","amount":8068259,"winner":["金益鼎企業股份有限公司"],"tender_api_url":"http://pcc.g0v.ronny.tw/api/tender?unit_id=3.13.50&job_number=MGF0550004","decisionDate":20170511}]},{"name":"揚昌汽車有限公司","total_amount":11450000,"item":[{"date":20170602,"file_name":"BDM-1-52151443","unit_name":"新竹市消防局","title":"新竹市消防局購置消防警備車11輛","amount":11450000,"winner":["揚昌汽車有限公司"],"tender_api_url":"http://pcc.g0v.ronny.tw/api/tender?unit_id=3.76.58.20&job_number=A106003","decisionDate":20170601}]},{"name":"洽隆企業有限公司","total_amount":34523568,"item":[{"date":20160321,"file_name":"BDM-1-51802820","unit_name":"財團法人國家衛生研究院","title":"實驗用氣體一批開口合約","amount":72150,"winner":["新大氣體有限公司","洽隆企業有限公司","信華氣體股份有限公司","亞東工業氣體股份有限公司"],"tender_api_url":"http://pcc.g0v.ronny.tw/api/tender?unit_id=92019239&job_number=05GC-0002","decisionDate":20160316},{"date":20170221,"file_name":"BDM-1-52075603","unit_name":"財團法人國家衛生研究院","title":"實驗用氣體1批開口合約","amount":48840,"winner":["新大氣體有限公司","洽隆企業有限公司","信華氣體股份有限公司"],"tender_api_url":"http://pcc.g0v.ronny.tw/api/tender?unit_id=92019239&job_number=06GC-0001","decisionDate":20170216},{"date":20170619,"file_name":"BDM-1-52164692","unit_name":"國立臺灣大學醫學院附設醫院新竹分院","title":"全院醫療氣體供應採購一批","amount":18532329,"winner":["洽隆企業有限公司"],"tender_api_url":"http://pcc.g0v.ronny.tw/api/tender?unit_id=3.9.20.1.4&job_number=HM060080","decisionDate":20170526},{"date":20170915,"file_name":"BDM-1-52237138","unit_name":"國立臺灣大學醫學院附設醫院新竹分院","title":"全院醫療氣體供應採購一批","amount":15870249,"winner":["洽隆企業有限公司"],"tender_api_url":"http://pcc.g0v.ronny.tw/api/tender?unit_id=3.9.20.1.4&job_number=HM060440","decisionDate":20170905}]}]},"prevPath":"elections/2016-legislator-election/regions/新竹市/constituencies/第01選區","constituency":{"name":"第01選區","candidates":[{"alternative_id":329,"isElected":true,"name":"柯建銘","numOfVote":90642,"partyName":"民主進步黨","rateOfVote":41.33,"detailLink":"/api/v1/legislatorElection/2016/candidates/329","finance":{"income":{"total":51641147,"items":[{"name":"個人捐贈收入","amount":21483455},{"name":"營利事業捐贈收入","amount":26915133},{"name":"政黨捐贈收入","amount":0},{"name":"人民團體捐贈收入","amount":3020000},{"name":"匿名捐贈","amount":222011},{"name":"其他收入","amount":548}]},"outcome":{"total":52187931,"items":[{"name":"人事費用支出","amount":55960},{"name":"宣傳支出","amount":36548691},{"name":"租用宣傳車輛支出","amount":0},{"name":"租用競選辦事處支","amount":1200000},{"name":"集會支出","amount":6076630},{"name":"交通旅運支出","amount":766241},{"name":"雜支支出","amount":6222119},{"name":"返還支出","amount":1296800},{"name":"繳庫支出","amount":0},{"name":"公共關係費用支出","amount":21490}]}}},{"alternative_id":330,"isElected":false,"name":"曾耀澂","numOfVote":1304,"partyName":"無黨籍及未經政黨推薦","rateOfVote":0.59,"detailLink":"/api/v1/legislatorElection/2016/candidates/330","finance":null},{"alternative_id":331,"isElected":false,"name":"林家宇","numOfVote":476,"partyName":"自由台灣黨","rateOfVote":0.21,"detailLink":"/api/v1/legislatorElection/2016/candidates/331","finance":null},{"alternative_id":332,"isElected":false,"name":"歐崇敬","numOfVote":4189,"partyName":"親民黨","rateOfVote":1.91,"detailLink":"/api/v1/legislatorElection/2016/candidates/332","finance":null},{"alternative_id":333,"isElected":false,"name":"魏揚","numOfVote":723,"partyName":"軍公教聯盟黨","rateOfVote":0.32,"detailLink":"/api/v1/legislatorElection/2016/candidates/333","finance":null},{"alternative_id":334,"isElected":false,"name":"吳淑敏","numOfVote":4151,"partyName":"無黨籍及未經政黨推薦","rateOfVote":1.89,"detailLink":"/api/v1/legislatorElection/2016/candidates/334","finance":null},{"alternative_id":335,"isElected":false,"name":"黃源甫","numOfVote":1185,"partyName":"無黨籍及未經政黨推薦","rateOfVote":0.54,"detailLink":"/api/v1/legislatorElection/2016/candidates/335","finance":null},{"alternative_id":336,"isElected":false,"name":"王榮德","numOfVote":381,"partyName":"無黨籍及未經政黨推薦","rateOfVote":0.17,"detailLink":"/api/v1/legislatorElection/2016/candidates/336","finance":null},{"alternative_id":337,"isElected":false,"name":"鄭正鈐","numOfVote":79951,"partyName":"中國國民黨","rateOfVote":36.45,"detailLink":"/api/v1/legislatorElection/2016/candidates/337","finance":null},{"alternative_id":338,"isElected":false,"name":"邱顯智","numOfVote":36309,"partyName":"時代力量","rateOfVote":16.55,"detailLink":"/api/v1/legislatorElection/2016/candidates/338","finance":null}]}}}